eamcvd/__init__.py
eamcvd/requlib/__init__.py
eamcvd-1.4.1.dist-info/METADATA
eamcvd-1.4.1.dist-info/WHEEL
eamcvd-1.4.1.dist-info/top_level.txt
eamcvd-1.4.1.dist-info/RECORD
